[{"trial_type":"multimodal","delivered_vibration_level":3,"delivered_pressure_level":2,"pump":0,"timestamp":0.017235994338989258,"valve":0},{"trial_type":"multimodal","delivered_vibration_level":3,"delivered_pressure_level":2,"pump":0,"timestamp":0.01725900173187256,"valve":0},{"trial_type":"multimodal","delivered_vibration_level":3,"delivered_pressure_level":2,"pump":0,"timestamp":9.693238973617554,"valve":10},{"trial_type":"multimodal","delivered_vibration_level":3,"delivered_pressure_level":2,"pump":0,"timestamp":9.908143997192383,"valve":20},{"trial_type":"multimodal","delivered_vibration_level":3,"delivered_pressure_level":2,"pump":0,"timestamp":10.342245936393738,"valve":50}]