[{"delivered_pressure_level":3,"trial_type":"multimodal","valve":0,"delivered_vibration_level":1,"timestamp":0.018214106559753418,"pump":0},{"delivered_pressure_level":3,"trial_type":"multimodal","valve":0,"delivered_vibration_level":1,"timestamp":0.01824009418487549,"pump":0},{"delivered_pressure_level":3,"trial_type":"multimodal","valve":10,"delivered_vibration_level":1,"timestamp":6.160025000572205,"pump":0},{"delivered_pressure_level":3,"trial_type":"multimodal","valve":20,"delivered_vibration_level":1,"timestamp":6.272942066192627,"pump":0},{"delivered_pressure_level":3,"trial_type":"multimodal","valve":20,"delivered_vibration_level":1,"timestamp":11.826740026473999,"pump":200},{"delivered_pressure_level":3,"trial_type":"multimodal","valve":20,"delivered_vibration_level":1,"timestamp":12.34249210357666,"pump":400},{"delivered_pressure_level":3,"trial_type":"multimodal","valve":20,"delivered_vibration_level":1,"timestamp":32.84603703022003,"pump":700}]