[{"delivered_vibration_level":3,"valve":0,"timestamp":0.017544984817504883,"pump":700,"trial_type":"vibration","delivered_pressure_level":3},{"delivered_vibration_level":3,"valve":10,"timestamp":3.1084539890289307,"pump":700,"trial_type":"vibration","delivered_pressure_level":3},{"delivered_vibration_level":3,"valve":20,"timestamp":3.2062519788742065,"pump":700,"trial_type":"vibration","delivered_pressure_level":3},{"delivered_vibration_level":3,"valve":50,"timestamp":3.3564679622650146,"pump":700,"trial_type":"vibration","delivered_pressure_level":3}]