[{"timestamp":0.017076969146728516,"delivered_pressure_level":1,"valve":0,"pump":0,"delivered_vibration_level":3,"trial_type":"multimodal"},{"timestamp":0.01710200309753418,"delivered_pressure_level":1,"valve":0,"pump":0,"delivered_vibration_level":3,"trial_type":"multimodal"},{"timestamp":1.4591809511184692,"delivered_pressure_level":1,"valve":10,"pump":0,"delivered_vibration_level":3,"trial_type":"multimodal"},{"timestamp":1.5561269521713257,"delivered_pressure_level":1,"valve":20,"pump":0,"delivered_vibration_level":3,"trial_type":"multimodal"},{"timestamp":1.6560920476913452,"delivered_pressure_level":1,"valve":50,"pump":0,"delivered_vibration_level":3,"trial_type":"multimodal"},{"timestamp":2.6235549449920654,"delivered_pressure_level":1,"valve":50,"pump":200,"delivered_vibration_level":3,"trial_type":"multimodal"}]