[{"delivered_pressure_level":4,"pump":0,"trial_type":"multimodal","delivered_vibration_level":3,"valve":0,"timestamp":0.018333911895751953},{"delivered_pressure_level":4,"pump":0,"trial_type":"multimodal","delivered_vibration_level":3,"valve":0,"timestamp":0.018360018730163574},{"delivered_pressure_level":4,"pump":0,"trial_type":"multimodal","delivered_vibration_level":3,"valve":10,"timestamp":6.36020290851593},{"delivered_pressure_level":4,"pump":0,"trial_type":"multimodal","delivered_vibration_level":3,"valve":20,"timestamp":6.473954916000366},{"delivered_pressure_level":4,"pump":0,"trial_type":"multimodal","delivered_vibration_level":3,"valve":50,"timestamp":6.590963959693909},{"delivered_pressure_level":4,"pump":200,"trial_type":"multimodal","delivered_vibration_level":3,"valve":50,"timestamp":8.358865976333618}]