[{"valve":0,"delivered_pressure_level":3,"trial_type":"vibration","delivered_vibration_level":2,"pump":700,"timestamp":0.017649054527282715},{"valve":10,"delivered_pressure_level":3,"trial_type":"vibration","delivered_vibration_level":2,"pump":700,"timestamp":1.9240880012512207},{"valve":20,"delivered_pressure_level":3,"trial_type":"vibration","delivered_vibration_level":2,"pump":700,"timestamp":2.0891770124435425},{"valve":50,"delivered_pressure_level":3,"trial_type":"vibration","delivered_vibration_level":2,"pump":700,"timestamp":2.623744010925293}]