[{"delivered_pressure_level":3,"timestamp":0.016619086265563965,"pump":700,"trial_type":"vibration","delivered_vibration_level":3,"valve":0},{"delivered_pressure_level":3,"timestamp":4.075165033340454,"pump":700,"trial_type":"vibration","delivered_vibration_level":3,"valve":10},{"delivered_pressure_level":3,"timestamp":4.1903650760650635,"pump":700,"trial_type":"vibration","delivered_vibration_level":3,"valve":20},{"delivered_pressure_level":3,"timestamp":4.340152978897095,"pump":700,"trial_type":"vibration","delivered_vibration_level":3,"valve":50},{"delivered_pressure_level":3,"timestamp":4.656822085380554,"pump":700,"trial_type":"vibration","delivered_vibration_level":3,"valve":100}]