[{"valve":0,"timestamp":0.01758897304534912,"delivered_vibration_level":0,"trial_type":"pressure","pump":0,"delivered_pressure_level":4},{"valve":0,"timestamp":1.807850956916809,"delivered_vibration_level":0,"trial_type":"pressure","pump":200,"delivered_pressure_level":4},{"valve":0,"timestamp":1.8561609983444214,"delivered_vibration_level":0,"trial_type":"pressure","pump":400,"delivered_pressure_level":4},{"valve":0,"timestamp":1.888935923576355,"delivered_vibration_level":0,"trial_type":"pressure","pump":700,"delivered_pressure_level":4},{"valve":0,"timestamp":1.9058079719543457,"delivered_vibration_level":0,"trial_type":"pressure","pump":999,"delivered_pressure_level":4}]