[{"delivered_vibration_level":4,"timestamp":0.01711905002593994,"valve":0,"pump":0,"trial_type":"multimodal","delivered_pressure_level":4},{"delivered_vibration_level":4,"timestamp":0.01714503765106201,"valve":0,"pump":0,"trial_type":"multimodal","delivered_pressure_level":4},{"delivered_vibration_level":4,"timestamp":1.624804973602295,"valve":0,"pump":200,"trial_type":"multimodal","delivered_pressure_level":4},{"delivered_vibration_level":4,"timestamp":2.306715965270996,"valve":10,"pump":200,"trial_type":"multimodal","delivered_pressure_level":4},{"delivered_vibration_level":4,"timestamp":2.556583046913147,"valve":20,"pump":200,"trial_type":"multimodal","delivered_pressure_level":4},{"delivered_vibration_level":4,"timestamp":2.789921998977661,"valve":50,"pump":200,"trial_type":"multimodal","delivered_pressure_level":4},{"delivered_vibration_level":4,"timestamp":4.524217963218689,"valve":100,"pump":200,"trial_type":"multimodal","delivered_pressure_level":4}]