[{"trial_type":"multimodal","timestamp":0.018867015838623047,"delivered_vibration_level":3,"pump":0,"delivered_pressure_level":2,"valve":0},{"trial_type":"multimodal","timestamp":0.01889193058013916,"delivered_vibration_level":3,"pump":0,"delivered_pressure_level":2,"valve":0},{"trial_type":"multimodal","timestamp":2.0741519927978516,"delivered_vibration_level":3,"pump":0,"delivered_pressure_level":2,"valve":10},{"trial_type":"multimodal","timestamp":2.139380931854248,"delivered_vibration_level":3,"pump":0,"delivered_pressure_level":2,"valve":20},{"trial_type":"multimodal","timestamp":2.2056679725646973,"delivered_vibration_level":3,"pump":0,"delivered_pressure_level":2,"valve":50},{"trial_type":"multimodal","timestamp":3.9243019819259644,"delivered_vibration_level":3,"pump":200,"delivered_pressure_level":2,"valve":50},{"trial_type":"multimodal","timestamp":4.006379961967468,"delivered_vibration_level":3,"pump":400,"delivered_pressure_level":2,"valve":50},{"trial_type":"multimodal","timestamp":4.089432001113892,"delivered_vibration_level":3,"pump":700,"delivered_pressure_level":2,"valve":50},{"trial_type":"multimodal","timestamp":4.5742340087890625,"delivered_vibration_level":3,"pump":400,"delivered_pressure_level":2,"valve":50}]