[{"timestamp":0.018401026725769043,"valve":0,"trial_type":"multimodal","delivered_pressure_level":2,"delivered_vibration_level":1,"pump":0},{"timestamp":0.018436074256896973,"valve":0,"trial_type":"multimodal","delivered_pressure_level":2,"delivered_vibration_level":1,"pump":0},{"timestamp":1.9585950374603271,"valve":10,"trial_type":"multimodal","delivered_pressure_level":2,"delivered_vibration_level":1,"pump":0},{"timestamp":5.640951037406921,"valve":10,"trial_type":"multimodal","delivered_pressure_level":2,"delivered_vibration_level":1,"pump":200},{"timestamp":6.207297086715698,"valve":10,"trial_type":"multimodal","delivered_pressure_level":2,"delivered_vibration_level":1,"pump":400},{"timestamp":8.474871039390564,"valve":10,"trial_type":"multimodal","delivered_pressure_level":2,"delivered_vibration_level":1,"pump":700}]