[{"valve":0,"pump":0,"timestamp":0.017438054084777832,"delivered_pressure_level":4,"trial_type":"multimodal","delivered_vibration_level":3},{"valve":0,"pump":0,"timestamp":0.01746201515197754,"delivered_pressure_level":4,"trial_type":"multimodal","delivered_vibration_level":3},{"valve":10,"pump":0,"timestamp":2.0586200952529907,"delivered_pressure_level":4,"trial_type":"multimodal","delivered_vibration_level":3},{"valve":20,"pump":0,"timestamp":2.2397570610046387,"delivered_pressure_level":4,"trial_type":"multimodal","delivered_vibration_level":3},{"valve":20,"pump":200,"timestamp":6.458673000335693,"delivered_pressure_level":4,"trial_type":"multimodal","delivered_vibration_level":3},{"valve":20,"pump":400,"timestamp":6.808040022850037,"delivered_pressure_level":4,"trial_type":"multimodal","delivered_vibration_level":3},{"valve":20,"pump":700,"timestamp":7.074406027793884,"delivered_pressure_level":4,"trial_type":"multimodal","delivered_vibration_level":3},{"valve":20,"pump":400,"timestamp":8.926168084144592,"delivered_pressure_level":4,"trial_type":"multimodal","delivered_vibration_level":3}]