[{"trial_type":"pressure","timestamp":0.01802206039428711,"pump":0,"delivered_pressure_level":4,"valve":0,"delivered_vibration_level":0},{"trial_type":"pressure","timestamp":2.691546082496643,"pump":200,"delivered_pressure_level":4,"valve":0,"delivered_vibration_level":0},{"trial_type":"pressure","timestamp":2.722596049308777,"pump":400,"delivered_pressure_level":4,"valve":0,"delivered_vibration_level":0},{"trial_type":"pressure","timestamp":2.755473017692566,"pump":700,"delivered_pressure_level":4,"valve":0,"delivered_vibration_level":0},{"trial_type":"pressure","timestamp":2.8065160512924194,"pump":999,"delivered_pressure_level":4,"valve":0,"delivered_vibration_level":0}]