[{"delivered_vibration_level":3,"timestamp":0.017889976501464844,"trial_type":"multimodal","pump":0,"valve":0,"delivered_pressure_level":4},{"delivered_vibration_level":3,"timestamp":0.017915010452270508,"trial_type":"multimodal","pump":0,"valve":0,"delivered_pressure_level":4},{"delivered_vibration_level":3,"timestamp":5.7586140632629395,"trial_type":"multimodal","pump":0,"valve":10,"delivered_pressure_level":4},{"delivered_vibration_level":3,"timestamp":5.83984899520874,"trial_type":"multimodal","pump":0,"valve":20,"delivered_pressure_level":4},{"delivered_vibration_level":3,"timestamp":6.00729501247406,"trial_type":"multimodal","pump":0,"valve":50,"delivered_pressure_level":4},{"delivered_vibration_level":3,"timestamp":9.258574962615967,"trial_type":"multimodal","pump":200,"valve":50,"delivered_pressure_level":4}]