[{"delivered_pressure_level":1,"delivered_vibration_level":4,"trial_type":"multimodal","timestamp":0.01746499538421631,"pump":0,"valve":0},{"delivered_pressure_level":1,"delivered_vibration_level":4,"trial_type":"multimodal","timestamp":0.01749598979949951,"pump":0,"valve":0},{"delivered_pressure_level":1,"delivered_vibration_level":4,"trial_type":"multimodal","timestamp":8.793035984039307,"pump":0,"valve":10},{"delivered_pressure_level":1,"delivered_vibration_level":4,"trial_type":"multimodal","timestamp":8.907688975334167,"pump":0,"valve":20},{"delivered_pressure_level":1,"delivered_vibration_level":4,"trial_type":"multimodal","timestamp":8.973955988883972,"pump":0,"valve":50},{"delivered_pressure_level":1,"delivered_vibration_level":4,"trial_type":"multimodal","timestamp":9.040462017059326,"pump":0,"valve":100},{"delivered_pressure_level":1,"delivered_vibration_level":4,"trial_type":"multimodal","timestamp":9.908736944198608,"pump":200,"valve":100},{"delivered_pressure_level":1,"delivered_vibration_level":4,"trial_type":"multimodal","timestamp":12.35916292667389,"pump":400,"valve":100},{"delivered_pressure_level":1,"delivered_vibration_level":4,"trial_type":"multimodal","timestamp":14.19227397441864,"pump":200,"valve":100}]