[{"timestamp":0.017559051513671875,"trial_type":"multimodal","valve":0,"pump":0,"delivered_pressure_level":4,"delivered_vibration_level":1},{"timestamp":0.017590045928955078,"trial_type":"multimodal","valve":0,"pump":0,"delivered_pressure_level":4,"delivered_vibration_level":1},{"timestamp":1.6591960191726685,"trial_type":"multimodal","valve":0,"pump":200,"delivered_pressure_level":4,"delivered_vibration_level":1},{"pump":400,"trial_type":"multimodal","timestamp":1.723618984222412,"valve":0,"delivered_pressure_level":4,"delivered_vibration_level":1},{"pump":700,"trial_type":"multimodal","timestamp":1.7559659481048584,"valve":0,"delivered_pressure_level":4,"delivered_vibration_level":1},{"pump":999,"trial_type":"multimodal","timestamp":1.7884069681167603,"valve":0,"delivered_pressure_level":4,"delivered_vibration_level":1},{"pump":999,"trial_type":"multimodal","timestamp":2.5406769514083862,"valve":10,"delivered_pressure_level":4,"delivered_vibration_level":1},{"pump":999,"trial_type":"multimodal","timestamp":2.9237500429153442,"valve":20,"delivered_pressure_level":4,"delivered_vibration_level":1}]